googlefinance/__init__.py
googlefinance/get.py
googlefinance.get-0.4.8.dist-info/DESCRIPTION.rst
googlefinance.get-0.4.8.dist-info/METADATA
googlefinance.get-0.4.8.dist-info/RECORD
googlefinance.get-0.4.8.dist-info/WHEEL
googlefinance.get-0.4.8.dist-info/metadata.json
googlefinance.get-0.4.8.dist-info/top_level.txt
