Metadata-Version: 2.0
Name: googlefinance.get
Version: 0.4.8
Summary: googlefinance.get is crawling the financial data from Google finance
Home-page: https://github.com/YongBeomKim/googlefinance.get
Author: Yong Beom Kim
Author-email: saltman21@naver.com
License: MIT
Download-URL: https://github.com/YongBeomKim/googlefinance.get/blob/master/dist/googlefinance.get-0.4.8-py2.py3-none-any.whl
Keywords: googlefinance
Platform: UNKNOWN
Classifier: Programming Language :: Python :: 3.6
Classifier: Intended Audience :: Financial and Insurance Industry
Classifier: License :: OSI Approved :: MIT License
Requires-Dist: requests
Requires-Dist: pandas
